ezml/__init__.py
ezml-1.1.2.dist-info/LICENSE
ezml-1.1.2.dist-info/METADATA
ezml-1.1.2.dist-info/WHEEL
ezml-1.1.2.dist-info/top_level.txt
ezml-1.1.2.dist-info/RECORD
