Metadata-Version: 2.1
Name: ezml
Version: 1.1.2
Summary: An (extremly) simple Meta-Language, this is the parser!
Home-page: https://github.com/chadgroom/EZML
Author: Chad M. Groom
Author-email: chadgroom17@gmail.com
License: UNKNOWN
Platform: UNKNOWN
Classifier: Programming Language :: Python :: 3
Classifier: License :: OSI Approved :: MIT License
Classifier: Operating System :: OS Independent
Requires-Python: >=3.6
